[
  {
    "author": "Амбасадор JuniorS",
    "rating": 5,
    "text": "Все було надзвичайно смачно та приємно! Атмосфера чудова, а обслуговування — на найвищому рівні. Особлива подяка офіціанту Павлу — швидко, уважно й з посмішкою! Порадив усе найкраще та зробив приємний бонус до Дня народження. Дякуємо за сервіс і турботу — обов’язково повернемось!",
    "time": "2 тижні тому",
    "restaurant_name": "Хачапурі та Вино",
    "restaurant_city": "Київ",
    "scraped_at": "2025-07-30T19:05:35.607801"
  },
  {
    "author": "Софія Фесун",
    "rating": 5,
    "text": "Затишне місце з гарною терасою, де можна чудово провести час та смачно поїсти. Окрема подяка офіціантці Дарині за уважність до кожного гостя та обслуговування на найвищому рівні❤️",
    "time": "місяць тому",
    "restaurant_name": "Хачапурі та Вино",
    "restaurant_city": "Київ",
    "scraped_at": "2025-07-30T19:05:35.607815"
  },
  {
    "author": "Марина Владиславівна Зерницька",
    "rating": 5,
    "text": "Дякуємо за смачну їжу!\nСтрави були справді на високому рівні — все свіже, ароматне й з любов’ю приготоване. Особливо сподобались хінкалі з сиром. Окрема подяка офіціантці Ніці — дуже…",
    "time": "2 тижні тому",
    "restaurant_name": "Хачапурі та Вино",
    "restaurant_city": "Київ",
    "scraped_at": "2025-07-30T19:05:35.607835"
  },
  {
    "author": "Arthur Holub",
    "rating": 5,
    "text": "Чудове місце, дуже смачно, красиво та приємний персонал, обслуговування на рівні.",
    "time": "3 тижні тому",
    "restaurant_name": "Хачапурі та Вино",
    "restaurant_city": "Київ",
    "scraped_at": "2025-07-30T19:05:35.607846"
  },
  {
    "author": "Антон Розомюк",
    "rating": 5,
    "text": "Дякуємо за чудовий вечір у вашому ресторані! Їжа була надзвичайно смачною, а атмосфера дуже приємною. Окрема подяка офіціантці Дарині за її уважність, професіоналізм та привітність. Вона зробила наш візит ще приємнішим! Обов'язково повернемося знову.",
    "time": "місяць тому",
    "restaurant_name": "Хачапурі та Вино",
    "restaurant_city": "Київ",
    "scraped_at": "2025-07-30T19:05:35.607857"
  },
  {
    "author": "Alexandr Kupriyanchuk",
    "rating": 5,
    "text": "Дуже тихе та затишне місце в мегаполісі, де насправді можна насолодитись атмосферою та неймовірною грузинською кухнею.\nВідмічу окрему адміністратора Дмитра, дуже ввічлива та порядна людина.…",
    "time": "місяць тому",
    "restaurant_name": "Хачапурі та Вино",
    "restaurant_city": "Київ",
    "scraped_at": "2025-07-30T19:05:35.607867"
  },
  {
    "author": "Ань Штерн",
    "rating": 5,
    "text": "Смачно годують, класна атмосфера. Офіціантка Аня чудова! Розказала і за акції і комплімент від закладу принесла 🥰 дякую!…",
    "time": "тиждень тому",
    "restaurant_name": "Хачапурі та Вино",
    "restaurant_city": "Київ",
    "scraped_at": "2025-07-30T19:05:35.607878"
  },
  {
    "author": "Maria Domanchuk",
    "rating": 5,
    "text": "Замовляли хачапурі по-аджарськи, хінкалі асорті та лимонад — все було надзвичайно смачно! Свіже, соковите й з любов’ю приготоване. Особлива подяка офіціанту Павлу — дуже ввічливий, усе детально пояснив і допоміг з вибором. Атмосфера приємна, сервіс на рівні. Щиро рекомендую цей заклад!",
    "time": "2 тижні тому",
    "restaurant_name": "Хачапурі та Вино",
    "restaurant_city": "Київ",
    "scraped_at": "2025-07-30T19:05:35.607888"
  },
  {
    "author": "Имя",
    "rating": 5,
    "text": "Все дуже сподобалось, обслуговувала офіціантка Вероніка,обслуговування на вищому рівні,привітлива,приємна в спілкуванні, порадила нам дуже смачні страви,допомогла з усіма питаннями,щира, доброзичлива,та й в цілому найкраща офіціантка,заклад дуже сподобався😊…",
    "time": "тиждень тому",
    "restaurant_name": "Хачапурі та Вино",
    "restaurant_city": "Київ",
    "scraped_at": "2025-07-30T19:05:35.607899"
  },
  {
    "author": "Ігор Довгань",
    "rating": 5,
    "text": "Чудове місце в серці Подолу\nСмачна їжа і спокійна атмосфера\nХочеться відзначити роботу офіціантів які проявляють уважність до гостей, замовлення готувались та подавались доволі швидко",
    "time": "3 тижні тому",
    "restaurant_name": "Хачапурі та Вино",
    "restaurant_city": "Київ",
    "scraped_at": "2025-07-30T19:05:35.607913"
  },
  {
    "author": "пес дюк",
    "rating": 5,
    "text": "Завітала разом з подругою до цього вишуканого місця, щоб насолодитися смаком грузинської кухні. Взяла собі лагман з телятиною. Він дуже соковитий й наповнений спеціями, дуже смачно. Надалі рекомендую хінкалі й хачапурі. Особливо остання…",
    "time": "2 місяці тому",
    "restaurant_name": "Хачапурі та Вино",
    "restaurant_city": "Київ",
    "scraped_at": "2025-07-30T19:05:35.607923"
  },
  {
    "author": "Анна Сергіївна Рябець",
    "rating": 5,
    "text": "дуже смачно! офіціант Павло допоміг зі всіма питаннями, атмосфера завдяки музиці та офіціанту просто супер!",
    "time": "2 тижні тому",
    "restaurant_name": "Хачапурі та Вино",
    "restaurant_city": "Київ",
    "scraped_at": "2025-07-30T19:05:35.607933"
  },
  {
    "author": "Ірина Кожухар",
    "rating": 5,
    "text": "Доброго дня, були на вихідних з друзями у вашому ресторані. Були дуже вражені атмосферою та інтерʼєром, відчували себе як вдома, завдяки ввічливому та турботливому персоналу,  офіціант постійно був поряд та приділяв багато уваги, враховуючи…",
    "time": "рік тому",
    "restaurant_name": "Хачапурі та Вино",
    "restaurant_city": "Київ",
    "scraped_at": "2025-07-30T19:05:35.607946"
  },
  {
    "author": "Valentina Galimova",
    "rating": 5,
    "text": "Чудовий ресторан! Чудове обслуговування! Особлива подяка менеджеру Дмитру!  За гарне вчасне Обслуговування!  Приємний интерєр! Смачна кухня! Повернемось обовязково!!! Дякуємо.",
    "time": "місяць тому",
    "restaurant_name": "Хачапурі та Вино",
    "restaurant_city": "Київ",
    "scraped_at": "2025-07-30T19:05:35.607957"
  },
  {
    "author": "Анастасия Зимова",
    "rating": 5,
    "text": "Офіціант Дмитро дуже якісно обслужив, ввічливий та приємний. Швидка подача страв, все було дуже смачно:)",
    "time": "тиждень тому",
    "restaurant_name": "Хачапурі та Вино",
    "restaurant_city": "Київ",
    "scraped_at": "2025-07-30T19:05:35.608083"
  },
  {
    "author": "alina shatsylo",
    "rating": 5,
    "text": "Дуже приємний заклад та хороший персонал. Сталось, що одна страва була пересоленою, то пані офіціантка перепросила кілька разів й десерт компліментом спакувала, хоч я й не мала претензії - всяке буває😌…",
    "time": "3 місяці тому",
    "restaurant_name": "Хачапурі та Вино",
    "restaurant_city": "Київ",
    "scraped_at": "2025-07-30T19:05:35.608102"
  },
  {
    "author": "Mega GOLDon",
    "rating": 5,
    "text": "Все дуже смачно, грузинська атмосфера справді відчувається! Привітливі офіціанти, особливо Вероніка, дуже хороша дівчинка",
    "time": "тиждень тому",
    "restaurant_name": "Хачапурі та Вино",
    "restaurant_city": "Київ",
    "scraped_at": "2025-07-30T19:05:35.608115"
  },
  {
    "author": "Данило Вальчук",
    "rating": 5,
    "text": "Чудовий заклад, із дуже смачною традиційною грузинською кухнею.\nАтмосфера приємна, в закладі спокійна музика.\nЩо стосується обслуговування це вау!…",
    "time": "4 місяці тому",
    "restaurant_name": "Хачапурі та Вино",
    "restaurant_city": "Київ",
    "scraped_at": "2025-07-30T19:05:35.608129"
  },
  {
    "author": "Анна Маркова",
    "rating": 5,
    "text": "Дуже затишне та приємне місце. Чисто і гарно. Максимально уважні офіціанти. Усі страви що замовила були дуже смачні😍\nДякую вам ♥️✨…",
    "time": "9 місяців тому",
    "restaurant_name": "Хачапурі та Вино",
    "restaurant_city": "Київ",
    "scraped_at": "2025-07-30T19:05:35.608141"
  },
  {
    "author": "Андрій Вайда",
    "rating": 5,
    "text": "Найкраща кухня в Києві, раджу сюди прийти це того варте. Також дуже приємний перснонал, особливо офіціантка Марія)",
    "time": "2 тижні тому",
    "restaurant_name": "Хачапурі та Вино",
    "restaurant_city": "Київ",
    "scraped_at": "2025-07-30T19:05:35.608154"
  },
  {
    "author": "Катя Максименко",
    "rating": 5,
    "text": "Затишний заклад, смачна їжа, привітний та уважний персонал 🥰\nДілилась гарною новиною з подругами , свідками чого став персонал закладу та згодом долучились до привітань , що було дуже неочікувано та приємно ☺️🥰 щиро вдячна )…",
    "time": "10 місяців тому",
    "restaurant_name": "Хачапурі та Вино",
    "restaurant_city": "Київ",
    "scraped_at": "2025-07-30T19:05:35.608167"
  },
  {
    "author": "Maksi Max",
    "rating": 5,
    "text": "Чудова їжа та хороший персонал, дуже дякую офіціанту Павлу за чудовий настрій та професійність, приємно що набирають молодий та відповідальний персонал.",
    "time": "2 тижні тому",
    "restaurant_name": "Хачапурі та Вино",
    "restaurant_city": "Київ",
    "scraped_at": "2025-07-30T19:05:35.608180"
  },
  {
    "author": "Олександр Мотроненко",
    "rating": 5,
    "text": "Дуже смачна кухня, окрема подяка офіціанту Павлу! Підняв настрій 😁…",
    "time": "тиждень тому",
    "restaurant_name": "Хачапурі та Вино",
    "restaurant_city": "Київ",
    "scraped_at": "2025-07-30T19:05:35.608201"
  },
  {
    "author": "Вікторія Ільчишена",
    "rating": 5,
    "text": "Ресторан чудовий! Атмосфера тепла, персонал уважний. Хачапурі просто неймовірні – ніжне тісто, багато сиру, ідеальний баланс смаків. Хінкалі теж смачні, а шашлик соковитий. 🔥…",
    "time": "4 місяці тому",
    "restaurant_name": "Хачапурі та Вино",
    "restaurant_city": "Київ",
    "scraped_at": "2025-07-30T19:05:35.608214"
  },
  {
    "author": "ігор лабунський",
    "rating": 5,
    "text": "Марія, офіціантка просто неймовірна, дуже вічлива та професійна, я рекомендую. Все було дуже смачно😍…",
    "time": "2 тижні тому",
    "restaurant_name": "Хачапурі та Вино",
    "restaurant_city": "Київ",
    "scraped_at": "2025-07-30T19:05:35.608227"
  },
  {
    "author": "Kira Bondarenko",
    "rating": 5,
    "text": "Раджу спробувати хінкалі із куркою і грибами😍 ну дуже смачно 😌 також нам  запропонували шоколадний торт, бюджетно і смачно 👍…",
    "time": "рік тому",
    "restaurant_name": "Хачапурі та Вино",
    "restaurant_city": "Київ",
    "scraped_at": "2025-07-30T19:05:35.608239"
  },
  {
    "author": "Наталия Семенюк",
    "rating": 5,
    "text": "Щиро вдячні!\nЧудове обслуговування!\nПрекрасна кухня!\nПодяка офіціанту Павлові.",
    "time": "тиждень тому",
    "restaurant_name": "Хачапурі та Вино",
    "restaurant_city": "Київ",
    "scraped_at": "2025-07-30T19:05:35.608250"
  },
  {
    "author": "Альона Бондаренко",
    "rating": 5,
    "text": "Це один із найкращих закладів, які я відвідувала👍 святкували тут День народження із сімʼєю, офіціант виніс тортик зі свічкою🥰 + фонтан на терасі додає атмосферу. Ну дуууже смачно, дякуємо і рекомендуємо…",
    "time": "11 місяців тому",
    "restaurant_name": "Хачапурі та Вино",
    "restaurant_city": "Київ",
    "scraped_at": "2025-07-30T19:05:35.608264"
  },
  {
    "author": "Марія Головатюк",
    "rating": 5,
    "text": "Заклад з приємною атмосферою, смачною кухнею та привітним обслуговуванням. Хінкалі неймовірно смачні!",
    "time": "рік тому",
    "restaurant_name": "Хачапурі та Вино",
    "restaurant_city": "Київ",
    "scraped_at": "2025-07-30T19:05:35.608278"
  },
  {
    "author": "Марія Дзюба 7 група",
    "rating": 5,
    "text": "Вайбова атмосфера, смачні та соковиті страви з м'яса, салати виглядають гарно і смакують так само🫶🏻\nПриємна та вічлива офіціант Дарина🫰🏻…",
    "time": "місяць тому",
    "restaurant_name": "Хачапурі та Вино",
    "restaurant_city": "Київ",
    "scraped_at": "2025-07-30T19:05:35.608289"
  },
  {
    "author": "Viktoriia Kartashova ART",
    "rating": 5,
    "text": "Гарний сучасний бізнес центр. Багато компаній міжнародних. Консультаційна компанія  PriceWaterHouseCoopers на 10 поверсі.",
    "time": "10 місяців тому",
    "restaurant_name": "Евразія",
    "restaurant_city": "Київ",
    "scraped_at": "2025-07-30T19:06:57.069835"
  },
  {
    "author": "Julia Karmaliyk",
    "rating": 5,
    "text": "Зручне розташування і смачні кафе внизу)",
    "time": "Змінено 7 років тому",
    "restaurant_name": "Евразія",
    "restaurant_city": "Київ",
    "scraped_at": "2025-07-30T19:06:57.069842"
  },
  {
    "author": "Олег Бойко",
    "rating": 5,
    "text": "Смачна кухня, реально смачний тартар! Салати, міні-чебуреки та ін. - дійсно смачно.",
    "time": "3 роки тому",
    "restaurant_name": "Евразія",
    "restaurant_city": "Київ",
    "scraped_at": "2025-07-30T19:06:57.069848"
  },
  {
    "author": "SAFIKA",
    "rating": 5,
    "text": "Дуже смачна кухня, ввічливий персонал і атмосфера супер! Рекомендую",
    "time": "5 років тому",
    "restaurant_name": "Евразія",
    "restaurant_city": "Київ",
    "scraped_at": "2025-07-30T19:06:57.069854"
  },
  {
    "author": "Валентина Кононова",
    "rating": 5,
    "text": "Затишна атмосфера. Швидко обслуговують, навіть телефон підзарядили.",
    "time": "7 років тому",
    "restaurant_name": "Евразія",
    "restaurant_city": "Київ",
    "scraped_at": "2025-07-30T19:06:57.069860"
  },
  {
    "author": "Дмитро Рудич",
    "rating": 5,
    "text": "Люблю \"забери сам\" коли подвійна порція за ціну одної ,смачні роли.",
    "time": "6 років тому",
    "restaurant_name": "Евразія",
    "restaurant_city": "Київ",
    "scraped_at": "2025-07-30T19:06:57.069866"
  },
  {
    "author": "Василь Чалапчій",
    "rating": 5,
    "text": "Бізнес центр..вхід по пропусках) на першому поверсі ресторани і кафешки...",
    "time": "8 років тому",
    "restaurant_name": "Евразія",
    "restaurant_city": "Київ",
    "scraped_at": "2025-07-30T19:06:57.069872"
  },
  {
    "author": "Sergiy Gutyuk",
    "rating": 5,
    "text": "Гарний офісний центр із гарними закладами для перекусу.",
    "time": "8 років тому",
    "restaurant_name": "Евразія",
    "restaurant_city": "Київ",
    "scraped_at": "2025-07-30T19:06:57.069877"
  },
  {
    "author": "Володимир Ющишин",
    "rating": 5,
    "text": "Хороший БЦ є підземний паркінг.",
    "time": "3 роки тому",
    "restaurant_name": "Евразія",
    "restaurant_city": "Київ",
    "scraped_at": "2025-07-30T19:06:57.069883"
  },
  {
    "author": "Ihor Kurylenko",
    "rating": 5,
    "text": "Концетрація всіх топ-компаній України",
    "time": "8 років тому",
    "restaurant_name": "Евразія",
    "restaurant_city": "Київ",
    "scraped_at": "2025-07-30T19:06:57.069889"
  },
  {
    "author": "Олег Водяник",
    "rating": 5,
    "text": "Гарна обстановка все ухожено.",
    "time": "8 років тому",
    "restaurant_name": "Евразія",
    "restaurant_city": "Київ",
    "scraped_at": "2025-07-30T19:06:57.069895"
  },
  {
    "author": "Іван Грицан",
    "rating": 5,
    "text": "Красива споруда у середмісті столиці.",
    "time": "8 років тому",
    "restaurant_name": "Евразія",
    "restaurant_city": "Київ",
    "scraped_at": "2025-07-30T19:06:57.069900"
  },
  {
    "author": "Андрій Салтанюк",
    "rating": 5,
    "text": "досить сучасний бізнес-центр.",
    "time": "9 років тому",
    "restaurant_name": "Евразія",
    "restaurant_city": "Київ",
    "scraped_at": "2025-07-30T19:06:57.069906"
  },
  {
    "author": "fumy GATOR (fumyGATOR)",
    "rating": 5,
    "text": "Гарне розташування офісів",
    "time": "6 років тому",
    "restaurant_name": "Евразія",
    "restaurant_city": "Київ",
    "scraped_at": "2025-07-30T19:06:57.069912"
  },
  {
    "author": "Andei Lomov",
    "rating": 5,
    "text": "Тут класно",
    "time": "5 років тому",
    "restaurant_name": "Евразія",
    "restaurant_city": "Київ",
    "scraped_at": "2025-07-30T19:06:57.069918"
  },
  {
    "author": "степан мосяк",
    "rating": 5,
    "text": "Непоганий готель",
    "time": "Змінено 7 років тому",
    "restaurant_name": "Евразія",
    "restaurant_city": "Київ",
    "scraped_at": "2025-07-30T19:06:57.069924"
  },
  {
    "author": "Serhii Puzyrko",
    "rating": 5,
    "text": "Затишно і комфортно",
    "time": "9 років тому",
    "restaurant_name": "Евразія",
    "restaurant_city": "Київ",
    "scraped_at": "2025-07-30T19:06:57.069929"
  },
  {
    "author": "Olga Rogulia",
    "rating": 5,
    "text": "Сучасний і помпезний",
    "time": "7 років тому",
    "restaurant_name": "Евразія",
    "restaurant_city": "Київ",
    "scraped_at": "2025-07-30T19:06:57.069935"
  },
  {
    "author": "Андрій Масленчук",
    "rating": 5,
    "text": "Хороше місце",
    "time": "7 років тому",
    "restaurant_name": "Евразія",
    "restaurant_city": "Київ",
    "scraped_at": "2025-07-30T19:06:57.069941"
  },
  {
    "author": "Свят Сологуб",
    "rating": 5,
    "text": "Європейський рівень.",
    "time": "3 роки тому",
    "restaurant_name": "Евразія",
    "restaurant_city": "Київ",
    "scraped_at": "2025-07-30T19:06:57.069953"
  },
  {
    "author": "Владислав",
    "rating": 5,
    "text": "Круте місце",
    "time": "6 років тому",
    "restaurant_name": "Евразія",
    "restaurant_city": "Київ",
    "scraped_at": "2025-07-30T19:06:57.069959"
  },
  {
    "author": "Ігор Розовенко",
    "rating": 5,
    "text": "Гарне місце",
    "time": "6 років тому",
    "restaurant_name": "Евразія",
    "restaurant_city": "Київ",
    "scraped_at": "2025-07-30T19:06:57.069965"
  },
  {
    "author": "Borys Zhuk",
    "rating": 5,
    "text": "Бізнес центр",
    "time": "7 років тому",
    "restaurant_name": "Евразія",
    "restaurant_city": "Київ",
    "scraped_at": "2025-07-30T19:06:57.069971"
  },
  {
    "author": "Lora",
    "rating": 5,
    "text": "Зручне розташування",
    "time": "6 років тому",
    "restaurant_name": "Евразія",
    "restaurant_city": "Київ",
    "scraped_at": "2025-07-30T19:06:57.069977"
  },
  {
    "author": "Matras House Магазин матраців та ліжок в Києві (Віктор Богатько)",
    "rating": 5,
    "text": "Цікаве місце",
    "time": "4 роки тому",
    "restaurant_name": "Евразія",
    "restaurant_city": "Київ",
    "scraped_at": "2025-07-30T19:06:57.069983"
  },
  {
    "author": "Alex Nedobor",
    "rating": 5,
    "text": "Чудове місце",
    "time": "5 років тому",
    "restaurant_name": "Евразія",
    "restaurant_city": "Київ",
    "scraped_at": "2025-07-30T19:06:57.069988"
  },
  {
    "author": "Olha M. Khekalo",
    "rating": 5,
    "text": "Ну дуже подобається нам тут! Багато разів сюди ходили, доки не розчарували. Тут суп дуже смачний і свіжий, і будь-які інші роли просто шик! В іншому місці Євразії як то розчарували, суп був ледве тепленький. Тут все супер! Можете сміливо…",
    "time": "8 років тому",
    "restaurant_name": "Евразія",
    "restaurant_city": "Київ",
    "scraped_at": "2025-07-30T19:06:57.069994"
  },
  {
    "author": "Аньчик Терещенко (Пушистый Еж)",
    "rating": 5,
    "text": "Хороший бізнес-центр. Зручне розташування, недалеко від вокзалу. Зупинка під входом. Поруч багато закладів та магазинів. Чисто, ліфти, банкомат. Проблема з паркуванням. 14 поверхів. Є рецепція, пропускна система. Якщо хочете потрапити всередину - потрібно мати з собою документи, що підтверджують особу.",
    "time": "5 років тому",
    "restaurant_name": "Евразія",
    "restaurant_city": "Київ",
    "scraped_at": "2025-07-30T19:06:57.070000"
  },
  {
    "author": "Vitalii Oliinyk",
    "rating": 5,
    "text": "БЦ із дуже зручним розташуванням. Можна швидко дістатися від метро різних гілок. Завжди привітний персонал. Поблизу багато кафе та ресторанів для бізнес-ланчів. Поруч парк для прогулянок влітку під час обіду.",
    "time": "7 років тому",
    "restaurant_name": "Евразія",
    "restaurant_city": "Київ",
    "scraped_at": "2025-07-30T19:06:57.070006"
  },
  {
    "author": "Max Olex-ch",
    "rating": 5,
    "text": "Нормально. У кроковій доступності немає супермаркету, якщо раптом потрібно придбати їжу. Натомість багато різних кафешок.\nДо \"Вокзальної\" близько 10 хвилин ходьби, до \"Олімпійської\" - близько 20.",
    "time": "7 років тому",
    "restaurant_name": "Евразія",
    "restaurant_city": "Київ",
    "scraped_at": "2025-07-30T19:06:57.070012"
  },
  {
    "author": "Alina",
    "rating": 5,
    "text": "Екстравагантна архітектура. Парковки немає, враховуйте це. Інтерʼєр в стилі мережі тож будьте готові до великої кількості дерева та мушлі. Свіжа риба, привітний персонал. Охайна вбиральня але без таблички (повісьте будь ласка, копійки ж вартує)",
    "time": "тиждень тому",
    "restaurant_name": "Чорноморка",
    "restaurant_city": "Київ",
    "scraped_at": "2025-07-30T19:08:04.524951"
  },
  {
    "author": "Iryna Ponomarenko",
    "rating": 5,
    "text": "Чорноморка — любов з першого укусу! 🐟🦪🍽️\n\nЦе був один з тих обідів, після яких хочеться сказати: “Ну от і все, тепер я…",
    "time": "2 місяці тому",
    "restaurant_name": "Чорноморка",
    "restaurant_city": "Київ",
    "scraped_at": "2025-07-30T19:08:04.524963"
  },
  {
    "author": "Алёна",
    "rating": 5,
    "text": "Сьогодні вперше відвідали Чорноморку.\nСмажена барабуля, теплий салат, карбонара з морепродуктами - неймовірні, дуже смачно. Окрема подяка офіціанту Олександру. Швидка подача. Рекомендуємо однозначно! 👍…",
    "time": "3 тижні тому",
    "restaurant_name": "Чорноморка",
    "restaurant_city": "Київ",
    "scraped_at": "2025-07-30T19:08:04.524976"
  },
  {
    "author": "Rina Kalo",
    "rating": 5,
    "text": "Смачний заклад з такими ж смачними морепродуктами! І юшка рибна класна, і ще пригощають окремо від замовлення юшкою з раками! Форшмак також сподобався! Салат «оселедець під шубою» та «мімоза» також суперські! Завжди свіжа рибка! І додому можна купити! Хто такий самий поціновувач морепродуктів і рибки, то вам сюди!",
    "time": "6 місяців тому",
    "restaurant_name": "Чорноморка",
    "restaurant_city": "Київ",
    "scraped_at": "2025-07-30T19:08:04.524986"
  },
  {
    "author": "Татьяна Коляда",
    "rating": 5,
    "text": "Дуже смачно 🤤\nЗадоволені всім! Приємна ціна, рибка свіжа і чудово приготована, їхній хумус - це гастрономічний оргазм)…",
    "time": "2 місяці тому",
    "restaurant_name": "Чорноморка",
    "restaurant_city": "Київ",
    "scraped_at": "2025-07-30T19:08:04.524996"
  },
  {
    "author": "Яна Комисар",
    "rating": 5,
    "text": "Смачно надзвичайно 👍 Все на вищому рівні : обслуговування,\nсмак та вигляд блюда, атмосфера … Офіціант 👍❤️ Дякуємо…",
    "time": "місяць тому",
    "restaurant_name": "Чорноморка",
    "restaurant_city": "Київ",
    "scraped_at": "2025-07-30T19:08:04.525006"
  },
  {
    "author": "Оля Хмелюк",
    "rating": 5,
    "text": "Дуже смачно ,дякуємо за чудове обслуговування.Ваша юшка неперевершена!!! За устриці 🦪 окрема подяка :великий вибір і всі дуже смачні .Приідемо ще до Вас на устриці ❤️❤️❤️…",
    "time": "3 місяці тому",
    "restaurant_name": "Чорноморка",
    "restaurant_city": "Київ",
    "scraped_at": "2025-07-30T19:08:04.525019"
  },
  {
    "author": "Оleksandr М&V",
    "rating": 5,
    "text": "Ресторан в центрі міста з великим вибором морепродуктів.\nЄ дві великі літні тераси, на одній з яких можно палити.\nРесторан великого розміру і навіть є дитяча площадка.…",
    "time": "рік тому",
    "restaurant_name": "Чорноморка",
    "restaurant_city": "Київ",
    "scraped_at": "2025-07-30T19:08:04.525038"
  },
  {
    "author": "Dmitry Todorovsky",
    "rating": 5,
    "text": "Завжди смачно та корисно, раджу для замовлення - устриці; барабулька чорноморська; мідії в сливочному соусі.",
    "time": "6 місяців тому",
    "restaurant_name": "Чорноморка",
    "restaurant_city": "Київ",
    "scraped_at": "2025-07-30T19:08:04.525050"
  },
  {
    "author": "Анастасія Климок",
    "rating": 5,
    "text": "Вдруге в Чорноморці на Васильківській, дуже смачно та атмосферно. Офіціант Богдар просто сонечко, зробив наш вечір максимально комфортним та приємним. Рекомендую до відвідування!)",
    "time": "3 місяці тому",
    "restaurant_name": "Чорноморка",
    "restaurant_city": "Київ",
    "scraped_at": "2025-07-30T19:08:04.525061"
  },
  {
    "author": "Vitalii",
    "rating": 5,
    "text": "UP 10.10.24. Смачні морепродукти, устриці особливо. Також сподобалось осінне меню, хоча фаршмак з грибами - історія не для кожного ;)…",
    "time": "Змінено 6 місяців тому",
    "restaurant_name": "Чорноморка",
    "restaurant_city": "Київ",
    "scraped_at": "2025-07-30T19:08:04.525072"
  },
  {
    "author": "Назарій Тодорів",
    "rating": 5,
    "text": "Чорноморка – це просто любов із першого візиту! Тут усе настільки смачно, що хочеться повернутися знову і знову. Смажена рибка – це окремий кайф: свіжа, хрустка, ідеально приготовлена. Кальмари теж порадували – ніжні й соковиті, злегка…",
    "time": "6 місяців тому",
    "restaurant_name": "Чорноморка",
    "restaurant_city": "Київ",
    "scraped_at": "2025-07-30T19:08:04.525083"
  },
  {
    "author": "Дмитро Михайлюк",
    "rating": 5,
    "text": "Заклад люкс, страви люкс. Сервіс, а саме, офіціант Дмитро, Люкс+\nУстриця «Голландський Принц» 10/10",
    "time": "5 місяців тому",
    "restaurant_name": "Чорноморка",
    "restaurant_city": "Київ",
    "scraped_at": "2025-07-30T19:08:04.525094"
  },
  {
    "author": "Julia Iskra",
    "rating": 5,
    "text": "Не розумію як так вийшло що тут досі немає мого відгуку, адже це мій улюблений київський ресторан 🤩 тут завжди неймовірно смачно, як страви основного меню так і спеціальні пропозиції, і сервіс завжди на висоті. Дякую, неодмінно прийду ще🥰…",
    "time": "7 місяців тому",
    "restaurant_name": "Чорноморка",
    "restaurant_city": "Київ",
    "scraped_at": "2025-07-30T19:08:04.525104"
  },
  {
    "author": "Євгенія Дудко",
    "rating": 5,
    "text": "класно відсвяткували день народження, затишно смачно та весело, офіціанти зробили наш вечір ще більш яскравим🤩…",
    "time": "6 місяців тому",
    "restaurant_name": "Чорноморка",
    "restaurant_city": "Київ",
    "scraped_at": "2025-07-30T19:08:04.525113"
  },
  {
    "author": "Alina Davydiak",
    "rating": 5,
    "text": "Обожнюю цей ресторан за смачну кухню та чудовий сервіс. Обслуговування в закладі на вищому рівні, дякую Максу за уважне та турботливе ставлення! Буду повертатися ще)",
    "time": "місяць тому",
    "restaurant_name": "Чорноморка",
    "restaurant_city": "Київ",
    "scraped_at": "2025-07-30T19:08:04.525123"
  },
  {
    "author": "D D",
    "rating": 5,
    "text": "Затишно, спокійно. Смачна їжа, швидка подача.",
    "time": "місяць тому",
    "restaurant_name": "Чорноморка",
    "restaurant_city": "Київ",
    "scraped_at": "2025-07-30T19:08:04.525133"
  },
  {
    "author": "Кристина Пилипович",
    "rating": 5,
    "text": "Була в Чорноморці на васильківській і хочу сказати , Чорноморка – це справжня знахідка для любителів свіжих морепродуктів та якісного сервісу. Відвідування цього ресторану залишило тільки найкращі враження!…",
    "time": "4 місяці тому",
    "restaurant_name": "Чорноморка",
    "restaurant_city": "Київ",
    "scraped_at": "2025-07-30T19:08:04.525143"
  },
  {
    "author": "Станіслав Кудін",
    "rating": 5,
    "text": "Нещодавно відвідав ресторан \"Чорноморка на олімпійській\", для зустрічі з другом якого давно не бачив,  і був вражений його затишною атмосферою, смачною їжею та чудовим сервісом.…",
    "time": "10 місяців тому",
    "restaurant_name": "Чорноморка",
    "restaurant_city": "Київ",
    "scraped_at": "2025-07-30T19:08:04.525154"
  },
  {
    "author": "Sasha Hulianytskui",
    "rating": 5,
    "text": "Дуже смачні страви. Особлива подяка офіціанту Дмитру - дуже обізнаний в меню і надзвичайно приємна в спілкуванні людина. Він зробив відвідування закладу в рази приємнішим. Обовʼязково завітаємо ще!",
    "time": "місяць тому",
    "restaurant_name": "Чорноморка",
    "restaurant_city": "Київ",
    "scraped_at": "2025-07-30T19:08:04.525169"
  },
  {
    "author": "Елена",
    "rating": 5,
    "text": "Дуже гарний ресторан.смачна кухня,ввічливий персонал.нас обслуговувала офіціант Валентина,дуже приємна дівчина.класний комплімент від ресторану-гаряча юшка.все дуже сподобалося. Дякуємо велике .",
    "time": "місяць тому",
    "restaurant_name": "Чорноморка",
    "restaurant_city": "Київ",
    "scraped_at": "2025-07-30T19:09:37.387121"
  },
  {
    "author": "Anton",
    "rating": 5,
    "text": "Дуже смачно пообідав у цьому закладі! Засмакувало усе: і пельмені з щуки і салат зі свіжих овочів, заправлений ароматною соняшниковою олією і безкоштовна рибна юшка (тут ключове слово «безкоштовна», але вона була цілком навіть добра на…",
    "time": "4 місяці тому",
    "restaurant_name": "Чорноморка",
    "restaurant_city": "Київ",
    "scraped_at": "2025-07-30T19:09:37.387131"
  },
  {
    "author": "Nadiia Kolpakova Olasiuk",
    "rating": 5,
    "text": "було чудово, як завжди в Чорноморці.\nприкро, що закінчилися устриці, вони обовʼязкові 💕\nАліна нам зробила вечір затишним і смачним, дякуємо ❤️❤️❤️…",
    "time": "місяць тому",
    "restaurant_name": "Чорноморка",
    "restaurant_city": "Київ",
    "scraped_at": "2025-07-30T19:09:37.387139"
  },
  {
    "author": "АЯ",
    "rating": 5,
    "text": "Улюблене місце всієї родини.\nДякуємо за благодійні акції і активності.\nСьогоднішнє свято для дітей - надзвичайне для душі і апетиту)…",
    "time": "місяць тому",
    "restaurant_name": "Чорноморка",
    "restaurant_city": "Київ",
    "scraped_at": "2025-07-30T19:09:37.387147"
  },
  {
    "author": "Ірина Долгова",
    "rating": 5,
    "text": "Смачний обід в Чорноморці.\nСвіжесенькі устриці - маст хев тут. Меню регулярно оновлюється, ми любимо цей заклад.…",
    "time": "4 місяці тому",
    "restaurant_name": "Чорноморка",
    "restaurant_city": "Київ",
    "scraped_at": "2025-07-30T19:09:37.387155"
  },
  {
    "author": "Володимир Великий",
    "rating": 5,
    "text": "Кращий ресторан де готують морепродукти. Все дуже смачно, великий вибір страв в мені є, а також можна купити охолоджену рибу. Люблю відвідувати даний заклад, завжди приємний персонал та гарна атмосфера.",
    "time": "6 місяців тому",
    "restaurant_name": "Чорноморка",
    "restaurant_city": "Київ",
    "scraped_at": "2025-07-30T19:09:37.387163"
  },
  {
    "author": "Татьяна Самойлюк",
    "rating": 5,
    "text": "Були в ресторані в суботу з чоловіком та донькою. Страви були як завжди смачні, офіціант Юрій супер молодець! Ми прийшли за 10 хвилин до закриття кухні, іЮрій все дуже швидко нам організував, порадив та обслужив на вищому рівні. Дуже вдячні!",
    "time": "6 днів тому",
    "restaurant_name": "Чорноморка",
    "restaurant_city": "Київ",
    "scraped_at": "2025-07-30T19:09:37.387171"
  },
  {
    "author": "Katrin",
    "rating": 5,
    "text": "Вже давно хотіла побувати і от нарешті) Спочатку, як зайшла, мені не сподобався інтер'єр, здавалося все таке старе, але потім я відчувала атмосферу того, що ти біля самого моря, запах риби, наче ти і не в Києві. Все було смачно, різні види…",
    "time": "рік тому",
    "restaurant_name": "Чорноморка",
    "restaurant_city": "Київ",
    "scraped_at": "2025-07-30T19:09:37.387179"
  },
  {
    "author": "Юлия Дацюк",
    "rating": 5,
    "text": "Враження від закладу лише позитивні. Тільки сіли за столик, дитині відразу принесли олівці і листок із завданнями для дітей, тож дитина не сумувала і не потрібно включати мультики. Прийшли ми повечеряти, в закладі було вільно тільки…",
    "time": "9 місяців тому",
    "restaurant_name": "Чорноморка",
    "restaurant_city": "Київ",
    "scraped_at": "2025-07-30T19:09:37.387187"
  },
  {
    "author": "Анастасия Кудашева",
    "rating": 5,
    "text": "Відпочивала з друзями вчора. Чудове місце для проведення часу у вихідний день. Атмосфера у закладі дуже приваблива і комфортна. Видно що все зроблено з любовʼю до своєї справи. Персонал дуже привітний. Час очікування страв не довгий , все…",
    "time": "3 тижні тому",
    "restaurant_name": "Чорноморка",
    "restaurant_city": "Київ",
    "scraped_at": "2025-07-30T19:09:37.387205"
  },
  {
    "author": "Любов Ходотай",
    "rating": 5,
    "text": "Дякую за теплу атмосферу, за уважність та ввічливість офіціата. Вчора купувала креветки тигрові, все почистити ще й рекомендацію дали як краще приготувати. Такої смакоти ще некуштувала. Дякую все на вищому рівні.",
    "time": "тиждень тому",
    "restaurant_name": "Чорноморка",
    "restaurant_city": "Київ",
    "scraped_at": "2025-07-30T19:09:37.387214"
  },
  {
    "author": "Денис Черкашин",
    "rating": 5,
    "text": "Чудове місце зі смачнющими стравами. Сервіс на висоті, а страви навіть чекати не довелось. Готують швидко (щоправда, це був будній день). Раджу завітати за можливості. Ті, хто любить їжу з морепродуктами, не пожалкуєте: її тут вміють готувати.",
    "time": "місяць тому",
    "restaurant_name": "Чорноморка",
    "restaurant_city": "Київ",
    "scraped_at": "2025-07-30T19:09:37.387222"
  },
  {
    "author": "Таня Грицюк",
    "rating": 5,
    "text": "Чудове місце, яке нам з подругою запамʼятається на все життя😂\nОфіціант Нікіта - лапочка❤️\nКласно зорієнтував по меню, з гумором як ми любимо❤️…",
    "time": "3 тижні тому",
    "restaurant_name": "Чорноморка",
    "restaurant_city": "Київ",
    "scraped_at": "2025-07-30T19:09:37.387230"
  },
  {
    "author": "Татьяна Опарий",
    "rating": 5,
    "text": "Як завжди смачно, обслуговування чудове. Місце де можна просто прийти швиденько,смачно та бюджетно поїсти. На трьох заплатили 1700 грн.",
    "time": "2 тижні тому",
    "restaurant_name": "Чорноморка",
    "restaurant_city": "Київ",
    "scraped_at": "2025-07-30T19:09:37.387238"
  },
  {
    "author": "Asuy Las",
    "rating": 5,
    "text": "Приїхали трішки видихнути і Черноморка як завжди на висоті! Офіціант Марк дуже круто і швидко обслужив і їжа просто неймовірна)\nЄдине но, брали креветки у фрітюрі, чистять їм стравохід, будь ласка, на смак не впливає, а на моральне розуміння дуже)\nДякую",
    "time": "3 тижні тому",
    "restaurant_name": "Чорноморка",
    "restaurant_city": "Київ",
    "scraped_at": "2025-07-30T19:09:37.387246"
  },
  {
    "author": "Арсений Геращенко",
    "rating": 5,
    "text": "Заклад дійсно чудовий, оазис серед міста, особливо коли тепло і є можливісьть сісти на терасі, здається ніби на березі моря.\nВ середині також цікавий інтерєр, аромат і  атмосфера моря, офіціанти і хостес…",
    "time": "9 місяців тому",
    "restaurant_name": "Чорноморка",
    "restaurant_city": "Київ",
    "scraped_at": "2025-07-30T19:09:37.387254"
  },
  {
    "author": "Крістіна Кузнєцова",
    "rating": 5,
    "text": "Найкраще місце в місті, дякуємо за привітність та дружнє обслуговування 😌✨. Пані Аліна дуже ввічлива, а офіціант Марк - ваш скарб. Обовʼязково повернемося до вас не раз!…",
    "time": "3 тижні тому",
    "restaurant_name": "Чорноморка",
    "restaurant_city": "Київ",
    "scraped_at": "2025-07-30T19:09:37.387262"
  },
  {
    "author": "Жанна Слободенюк",
    "rating": 5,
    "text": "Відвідала цей ресторан і залишилася у захваті! Морепродукти – свіжі, добре приготовані, особливо сподобалися устриці та грильовані креветки. Атмосфера затишна, інтер’єр стильний, а обслуговування – на вищому рівні. Офіціанти уважні,…",
    "time": "4 місяці тому",
    "restaurant_name": "Чорноморка",
    "restaurant_city": "Київ",
    "scraped_at": "2025-07-30T19:09:37.387270"
  },
  {
    "author": "Iryna Fenenko",
    "rating": 5,
    "text": "Як завжди все на висоті: персонал, морепродукти, атмосфера. Ціни приємні як для такого рівня сервісу та якості. Справжня знахідка для всіх хто любить рибу та морепродукти. Затишна рибальська хижина.",
    "time": "місяць тому",
    "restaurant_name": "Чорноморка",
    "restaurant_city": "Київ",
    "scraped_at": "2025-07-30T19:09:37.387278"
  },
  {
    "author": "Ваня Дудник",
    "rating": 5,
    "text": "Дуже смачно, неймовірна  атмосфера, дуже класні працівники, неймовірні офіціанти, розповіли все про меню, дуже сподобалось, залишились одні позитивні емоції.",
    "time": "3 тижні тому",
    "restaurant_name": "Чорноморка",
    "restaurant_city": "Київ",
    "scraped_at": "2025-07-30T19:09:37.387288"
  },
  {
    "author": "Volodymyr K",
    "rating": 5,
    "text": "Вперше тут. Смачно, комфортно, привітний персонал. Приємна музика. Приємний бонус від закладу у вигляді креветкової пасти з хвостом креветки. Чисто і у залі і у сан.вузлі. Молодці. Так тримати. Прийдемо ще)",
    "time": "7 місяців тому",
    "restaurant_name": "Чорноморка",
    "restaurant_city": "Київ",
    "scraped_at": "2025-07-30T19:09:37.387296"
  },
  {
    "author": "Вася Гафіянич",
    "rating": 5,
    "text": "дуже привітний персонал, все смачно та оперативно, морепродукти на вищому рівні, чудово провели час з друзями. рекомендую !",
    "time": "3 тижні тому",
    "restaurant_name": "Чорноморка",
    "restaurant_city": "Київ",
    "scraped_at": "2025-07-30T19:09:37.387304"
  },
  {
    "author": "Олег Сидоренко",
    "rating": 5,
    "text": "Нещодавно відвідали ваш заклад і залишилися під приємними враженнями. Привітний адміністратор Аліна, уважний до деталей офіціант Максим, смачні страви та тепла , домашня атмосфера. Дякуємо за гарні емоції та позитив",
    "time": "3 тижні тому",
    "restaurant_name": "Чорноморка",
    "restaurant_city": "Київ",
    "scraped_at": "2025-07-30T19:09:37.387312"
  },
  {
    "author": "Moses Cummings",
    "rating": 5,
    "text": "Якщо хочеться риби або морепродуктів неодмінно треба йти в чорноморку. Вона тут завжди свіжа та смачно приготовлена. А атмосфера закладу взагалі неповторна, починаючи від інтер'єру закунчуючи песроналом, тут просто приємно провести час.",
    "time": "11 місяців тому",
    "restaurant_name": "Чорноморка",
    "restaurant_city": "Київ",
    "scraped_at": "2025-07-30T19:09:37.387322"
  },
  {
    "author": "Kristina Novitska",
    "rating": 5,
    "text": "Дійсно дивне розташування закладу, проте дуже сподобалось🤍\nХороше обслуговування, привітний адміністратор зустрічає на вході в пропонує різні варіанти столиків.…",
    "time": "4 роки тому",
    "restaurant_name": "Чорноморка",
    "restaurant_city": "Київ",
    "scraped_at": "2025-07-30T19:09:37.387330"
  },
  {
    "author": "Олексій Гребенюк",
    "rating": 5,
    "text": "Вітаю! Вчора вперше відвідав ваш заклад - і не пожалкував! Все супер смачно, атмосфера гостинності і професійний офіціант зробили свою справу - хочеться завітати ще))…",
    "time": "2 місяці тому",
    "restaurant_name": "Чорноморка",
    "restaurant_city": "Київ",
    "scraped_at": "2025-07-30T19:09:37.387338"
  },
  {
    "author": "Анастасія Серединська",
    "rating": 5,
    "text": "У вас дуже смачно та атмосферно. Дякуємо за лавандовий букетик, за професійність офіціантів та за смачні поради щодо вибору як страв, так і напоїв 🫶…",
    "time": "3 тижні тому",
    "restaurant_name": "Чорноморка",
    "restaurant_city": "Київ",
    "scraped_at": "2025-07-30T19:09:37.387346"
  },
  {
    "author": "Анжела Билак",
    "rating": 5,
    "text": "Дякуємо Аліні за гарний настрій та Ярославу за високий рівень професіоналізму!!! Так тримати, ми у вас не перший і точно не останній раз, любимо ваш заклад🫂…",
    "time": "3 тижні тому",
    "restaurant_name": "Чорноморка",
    "restaurant_city": "Київ",
    "scraped_at": "2025-07-30T19:09:37.387354"
  },
  {
    "author": "Kyïvan K.",
    "rating": 5,
    "text": "чудово, що в Києві з'явилася ця ресторанна мережа. раніше бував на Подолі, а от вперше не в центральному районі, а на Солом'янці - вул. Преображенська. заклад популярний - навіть вдень в робочий день зайнята половина доступних місць. воно і…",
    "time": "3 роки тому",
    "restaurant_name": "Чорноморка",
    "restaurant_city": "Київ",
    "scraped_at": "2025-07-30T19:09:37.387363"
  },
  {
    "author": "Alina Mayakovska",
    "rating": 5,
    "text": "Дякуємо за смачний сніданок! Завжди свіжий асортимент, величезний вибір страв та ввічливий персонал. Ви - найкращі 🔥…",
    "time": "3 тижні тому",
    "restaurant_name": "Чорноморка",
    "restaurant_city": "Київ",
    "scraped_at": "2025-07-30T19:09:37.387371"
  }
]